contexto/__init__.py
contexto/comparacion.py
contexto/correccion.py
contexto/escritura.py
contexto/exploracion.py
contexto/lectura.py
contexto/lematizacion.py
contexto/lenguajes.py
contexto/limpieza.py
contexto/stemming.py
contexto/vectorizacion.py
contexto/data/listas_stopwords/apellidos.txt
contexto/data/listas_stopwords/departamentos_col.txt
contexto/data/listas_stopwords/municipios_col.txt
contexto/data/listas_stopwords/nombres_ambos.txt
contexto/data/listas_stopwords/nombres_hombres.txt
contexto/data/listas_stopwords/nombres_mujeres.txt
contexto/data/listas_stopwords/sw_es.txt
contexto/utils/__init__.py
contexto/utils/auxiliares.py
contexto/utils/coocurrence_plot.py
contexto/utils/dispersion_plot.py
contexto/utils/limpieza_aux.py
contexto/utils/ocr.py
contexto/utils/pre_ocr.py
contexto/utils/spacy_funcs.py
contexto/utils/stanza_funcs.py
contexto/utils/tokenizacion.py
ConTexto-0.2.0.dist-info/LICENSE
ConTexto-0.2.0.dist-info/METADATA
ConTexto-0.2.0.dist-info/WHEEL
ConTexto-0.2.0.dist-info/top_level.txt
ConTexto-0.2.0.dist-info/RECORD
