Metadata-Version: 2.1
Name: ConTexto
Version: 0.2.0
Summary: Librería para el procesamiento y análisis de texto con Python
Home-page: https://github.com/ucd-dnp/ConTexto
Author: Departamento Nacional de Planeación - DNP
Author-email: ucd@dnp.gov.co
Maintainer: Unidad de Científicos de Datos - UCD
Maintainer-email: ucd@dnp.gov.co
License: MIT
Project-URL: Documentación, https://ucd-dnp.github.io/contexto/
Project-URL: Seguimiento de fallas, https://github.com/ucd-dnp/ConTexto/issues
Keywords: Python,OCR,NLP,Español,Text processing,UCD,DNP
Platform: UNKNOWN
Classifier: License :: OSI Approved :: MIT License
Classifier: Operating System :: Microsoft :: Windows
Classifier: Operating System :: POSIX :: Linux
Classifier: Programming Language :: Python :: 3
Classifier: Programming Language :: Python :: 3.6
Classifier: Programming Language :: Python :: 3.7
Classifier: Programming Language :: Python :: 3.8
Classifier: Programming Language :: Python :: 3.9
Requires-Python: >=3.6.2
License-File: LICENSE
Requires-Dist: click (<7.2.0,>=7.1.1)
Requires-Dist: docx2txt (==0.8)
Requires-Dist: gensim (==4.0.1)
Requires-Dist: googletrans (==2.4.0)
Requires-Dist: jellyfish (==0.8.2)
Requires-Dist: langid (==1.1.6)
Requires-Dist: matplotlib (>=3.3.4)
Requires-Dist: networkx (==2.5.1)
Requires-Dist: nltk (==3.6.2)
Requires-Dist: pandas (>=0.25.3)
Requires-Dist: pdf2image (==1.16.0)
Requires-Dist: PyPDF2 (==1.26.0)
Requires-Dist: pyspellchecker (==0.6.2)
Requires-Dist: python-docx (>=0.8.11)
Requires-Dist: opencv-python (>=4.5.2.54)
Requires-Dist: reportlab (==3.5.68)
Requires-Dist: scikit-learn (>=0.24.2)
Requires-Dist: slate3k (==0.5.3)
Requires-Dist: spacy (>=3.0.6)
Requires-Dist: stanza (>=1.2.1)
Requires-Dist: wordcloud (>=1.8.1)
Requires-Dist: pywin32 (>=227) ; platform_system == "Windows"
Requires-Dist: pytesseract (==0.3.7) ; python_version < "3.8.4"
Requires-Dist: pytesseract (>=0.3.7) ; python_version >= "3.8.5"
